bont/__init__.py
bont/bont.py
bont/models/__init__.py
bont/models/font_atlas.py
bont/models/glyph.py
bont-1.0.0.dist-info/METADATA
bont-1.0.0.dist-info/WHEEL
bont-1.0.0.dist-info/licenses/LICENSE
bont-1.0.0.dist-info/RECORD
