Metadata-Version: 2.3
Name: bont
Version: 1.0.0
Summary: A Python module for converting TrueType fonts to bitmap font texture atlas.
Project-URL: Homepage, https://github.com/kennedy0/bont
Author: Andrew Kennedy
License-File: LICENSE
Keywords: game development,pygame
Classifier: License :: OSI Approved :: MIT License
Classifier: Operating System :: OS Independent
Classifier: Programming Language :: Python :: 3
Requires-Python: >=3.12
Requires-Dist: fonttools
Requires-Dist: pillow
